monistode_binutils/__init__.py
monistode_binutils-0.1.10.dist-info/METADATA
monistode_binutils-0.1.10.dist-info/WHEEL
monistode_binutils-0.1.10.dist-info/RECORD
