Metadata-Version: 2.1
Name: monistode-binutils
Version: 0.1.10
Summary: A meta-repository for the Monistode binutils.
Author: rizerphe
Author-email: 44440399+rizerphe@users.noreply.github.com
Requires-Python: >=3.11,<4.0
Classifier: Programming Language :: Python :: 3
Classifier: Programming Language :: Python :: 3.11
Requires-Dist: monistode-assembler (>=0.1.16,<0.2.0)
Requires-Dist: monistode-linker (>=0.1.6,<0.2.0)
